<annotation>
	<folder>Dataset</folder>
	<filename>036.jpg</filename>
	<path>/Users/marina/Desktop/dataset_git/Dataset/036.jpg</path>
	<source>
		<database>Unknown</database>
	</source>
	<size>
		<width>1080</width>
		<height>1920</height>
		<depth>3</depth>
	</size>
	<segmented>0</segmented>
	<object>
		<name>Gray square</name>
		<pose>Unspecified</pose>
		<truncated>0</truncated>
		<difficult>0</difficult>
		<bndbox>
			<xmin>484</xmin>
			<ymin>1224</ymin>
			<xmax>663</xmax>
			<ymax>1424</ymax>
		</bndbox>
	</object>
	<object>
		<name>Gray four</name>
		<pose>Unspecified</pose>
		<truncated>0</truncated>
		<difficult>0</difficult>
		<bndbox>
			<xmin>602</xmin>
			<ymin>1006</ymin>
			<xmax>741</xmax>
			<ymax>1130</ymax>
		</bndbox>
	</object>
	<object>
		<name>Gray heart</name>
		<pose>Unspecified</pose>
		<truncated>0</truncated>
		<difficult>0</difficult>
		<bndbox>
			<xmin>394</xmin>
			<ymin>804</ymin>
			<xmax>553</xmax>
			<ymax>957</ymax>
		</bndbox>
	</object>
	<object>
		<name>Gray circle</name>
		<pose>Unspecified</pose>
		<truncated>0</truncated>
		<difficult>0</difficult>
		<bndbox>
			<xmin>357</xmin>
			<ymin>597</ymin>
			<xmax>498</xmax>
			<ymax>736</ymax>
		</bndbox>
	</object>
	<object>
		<name>Gray A-letter</name>
		<pose>Unspecified</pose>
		<truncated>1</truncated>
		<difficult>0</difficult>
		<bndbox>
			<xmin>1</xmin>
			<ymin>667</ymin>
			<xmax>165</xmax>
			<ymax>842</ymax>
		</bndbox>
	</object>
	<object>
		<name>Gray hexagon</name>
		<pose>Unspecified</pose>
		<truncated>1</truncated>
		<difficult>0</difficult>
		<bndbox>
			<xmin>1</xmin>
			<ymin>946</ymin>
			<xmax>96</xmax>
			<ymax>1114</ymax>
		</bndbox>
	</object>
	<object>
		<name>Gray star</name>
		<pose>Unspecified</pose>
		<truncated>0</truncated>
		<difficult>0</difficult>
		<bndbox>
			<xmin>269</xmin>
			<ymin>1044</ymin>
			<xmax>432</xmax>
			<ymax>1226</ymax>
		</bndbox>
	</object>
	<object>
		<name>Gray ring</name>
		<pose>Unspecified</pose>
		<truncated>0</truncated>
		<difficult>0</difficult>
		<bndbox>
			<xmin>98</xmin>
			<ymin>1152</ymin>
			<xmax>239</xmax>
			<ymax>1303</ymax>
		</bndbox>
	</object>
	<object>
		<name>Gray gear</name>
		<pose>Unspecified</pose>
		<truncated>1</truncated>
		<difficult>0</difficult>
		<bndbox>
			<xmin>1</xmin>
			<ymin>1354</ymin>
			<xmax>182</xmax>
			<ymax>1524</ymax>
		</bndbox>
	</object>
</annotation>
