<annotation>
	<folder>Dataset</folder>
	<filename>200.jpg</filename>
	<path>/Users/marina/Desktop/dataset_git/Dataset/200.jpg</path>
	<source>
		<database>Unknown</database>
	</source>
	<size>
		<width>960</width>
		<height>1280</height>
		<depth>3</depth>
	</size>
	<segmented>0</segmented>
	<object>
		<name>Gray A-letter</name>
		<pose>Unspecified</pose>
		<truncated>0</truncated>
		<difficult>0</difficult>
		<bndbox>
			<xmin>440</xmin>
			<ymin>984</ymin>
			<xmax>597</xmax>
			<ymax>1167</ymax>
		</bndbox>
	</object>
	<object>
		<name>Gray four</name>
		<pose>Unspecified</pose>
		<truncated>0</truncated>
		<difficult>0</difficult>
		<bndbox>
			<xmin>207</xmin>
			<ymin>403</ymin>
			<xmax>349</xmax>
			<ymax>513</ymax>
		</bndbox>
	</object>
	<object>
		<name>Gray ring</name>
		<pose>Unspecified</pose>
		<truncated>0</truncated>
		<difficult>0</difficult>
		<bndbox>
			<xmin>326</xmin>
			<ymin>557</ymin>
			<xmax>449</xmax>
			<ymax>682</ymax>
		</bndbox>
	</object>
	<object>
		<name>Gray heart</name>
		<pose>Unspecified</pose>
		<truncated>0</truncated>
		<difficult>0</difficult>
		<bndbox>
			<xmin>468</xmin>
			<ymin>505</ymin>
			<xmax>589</xmax>
			<ymax>627</ymax>
		</bndbox>
	</object>
	<object>
		<name>Gray square</name>
		<pose>Unspecified</pose>
		<truncated>0</truncated>
		<difficult>0</difficult>
		<bndbox>
			<xmin>451</xmin>
			<ymin>689</ymin>
			<xmax>616</xmax>
			<ymax>870</ymax>
		</bndbox>
	</object>
	<object>
		<name>Gray hexagon</name>
		<pose>Unspecified</pose>
		<truncated>0</truncated>
		<difficult>0</difficult>
		<bndbox>
			<xmin>751</xmin>
			<ymin>522</ymin>
			<xmax>899</xmax>
			<ymax>670</ymax>
		</bndbox>
	</object>
	<object>
		<name>Gray circle</name>
		<pose>Unspecified</pose>
		<truncated>0</truncated>
		<difficult>0</difficult>
		<bndbox>
			<xmin>594</xmin>
			<ymin>796</ymin>
			<xmax>732</xmax>
			<ymax>936</ymax>
		</bndbox>
	</object>
	<object>
		<name>Gray gear</name>
		<pose>Unspecified</pose>
		<truncated>0</truncated>
		<difficult>0</difficult>
		<bndbox>
			<xmin>375</xmin>
			<ymin>850</ymin>
			<xmax>520</xmax>
			<ymax>1005</ymax>
		</bndbox>
	</object>
	<object>
		<name>Gray star</name>
		<pose>Unspecified</pose>
		<truncated>0</truncated>
		<difficult>0</difficult>
		<bndbox>
			<xmin>202</xmin>
			<ymin>805</ymin>
			<xmax>368</xmax>
			<ymax>982</ymax>
		</bndbox>
	</object>
</annotation>
