<annotation>
	<folder>Dataset</folder>
	<filename>244.jpg</filename>
	<path>/Users/marina/Desktop/dataset_git/Dataset/244.jpg</path>
	<source>
		<database>Unknown</database>
	</source>
	<size>
		<width>960</width>
		<height>1280</height>
		<depth>3</depth>
	</size>
	<segmented>0</segmented>
	<object>
		<name>Orange gear</name>
		<pose>Unspecified</pose>
		<truncated>0</truncated>
		<difficult>0</difficult>
		<bndbox>
			<xmin>299</xmin>
			<ymin>627</ymin>
			<xmax>495</xmax>
			<ymax>824</ymax>
		</bndbox>
	</object>
	<object>
		<name>Orange star</name>
		<pose>Unspecified</pose>
		<truncated>0</truncated>
		<difficult>0</difficult>
		<bndbox>
			<xmin>476</xmin>
			<ymin>365</ymin>
			<xmax>699</xmax>
			<ymax>600</ymax>
		</bndbox>
	</object>
</annotation>
